LICENSE
pyproject.toml
readme.md
src/zen_util/__init__.py
src/zen_util/check_dict.py
src/zen_util/handle_plural.py
src/zen_util/nodupflatlist.py
src/zen_util/pretty_print.py
src/zen_util/replace_file_line.py
src/zen_util/update_init.py
src/zen_util/walk_dict.py
src/zen_util.egg-info/PKG-INFO
src/zen_util.egg-info/SOURCES.txt
src/zen_util.egg-info/dependency_links.txt
src/zen_util.egg-info/requires.txt
src/zen_util.egg-info/top_level.txt