Metadata-Version: 2.1
Name: zen_util
Version: 1.0.0
Summary: Zen utility library, helpful utility functions and decorators.
Author-email: Desultory <dev@pyl.onl>
Project-URL: Homepage, https://github.com/desultory/zen-util
Project-URL: Issues, https://github.com/desultory/zen-util/issues
Classifier: Programming Language :: Python :: 3
Classifier: License :: OSI Approved :: GNU General Public License v2 (GPLv2)
Classifier: Operating System :: OS Independent
Requires-Python: >=3.9
License-File: LICENSE
Requires-Dist: zen_logging>=1.0.0
